a_pandas_ex_csv_plus/LICENSE
a_pandas_ex_csv_plus/README.MD
a_pandas_ex_csv_plus/__init__.py
a_pandas_ex_csv_plus/requirements.txt
a_pandas_ex_csv_plus/thirdparty.json
a_pandas_ex_csv_plus-0.10.dist-info/LICENSE.rst
a_pandas_ex_csv_plus-0.10.dist-info/METADATA
a_pandas_ex_csv_plus-0.10.dist-info/WHEEL
a_pandas_ex_csv_plus-0.10.dist-info/top_level.txt
a_pandas_ex_csv_plus-0.10.dist-info/RECORD
