Metadata-Version: 2.1
Name: a-pandas-ex-csv-plus
Version: 0.10
Summary: When pd.read_csv(csvstring, sep=r'\s+') doesn't work ... 
Home-page: https://github.com/hansalemaos/a_pandas_ex_csv_plus
Author: Johannes Fischer
Author-email: <aulasparticularesdealemaosp@gmail.com>
License: MIT
Keywords: csv,pandas,DataFrame,read
Classifier: Development Status :: 4 - Beta
Classifier: Programming Language :: Python :: 3 :: Only
Classifier: Programming Language :: Python :: 3.9
Classifier: Topic :: Scientific/Engineering :: Visualization
Classifier: Topic :: Software Development :: Libraries :: Python Modules
Classifier: Topic :: Text Editors :: Text Processing
Classifier: Topic :: Text Processing :: General
Classifier: Topic :: Text Processing :: Indexing
Classifier: Topic :: Text Processing :: Filters
Classifier: Topic :: Utilities
License-File: LICENSE.rst
